djangocms_slides
