Metadata-Version: 1.1
Name: djangocms-slides
Version: 1.0.1
Summary: djangoCMS plugin for simple features, galleries or sliders
Home-page: http://www.django-cms.org/
Author: Ales Kocjancic
Author-email: alesdotio@gmail.com
License: MIT License
Platform: OS Independent
Classifier: Environment :: Web Environment
Classifier: Framework :: Django
Classifier: Intended Audience :: Developers
Classifier: License :: OSI Approved :: MIT License
Classifier: Operating System :: OS Independent
Classifier: Programming Language :: Python
Classifier: Topic :: Software Development :: Libraries :: Application Frameworks
Classifier: Topic :: Internet :: WWW/HTTP :: Dynamic Content
